setup.py
pinq/__init__.py
pinq/pinq.py
simple_pinq.egg-info/PKG-INFO
simple_pinq.egg-info/SOURCES.txt
simple_pinq.egg-info/dependency_links.txt
simple_pinq.egg-info/top_level.txt
simple_pinq.egg-info/zip-safe