Metadata-Version: 1.1
Name: simple-pinq
Version: 1.0.1
Summary: LINQ style API for Python.
Home-page: https://github.com/tizz98/pinq
Author: Elijah Wilson
Author-email: elijah@elijahwilson.me
License: MIT
Download-URL: https://github.com/tizz98/pinq/tarball/1.0.1
Keywords: linq pinq api
Platform: UNKNOWN
Classifier: Intended Audience :: Developers
Classifier: Topic :: Software Development :: Libraries
Classifier: License :: OSI Approved :: MIT License
Classifier: Programming Language :: Python :: 3
Classifier: Programming Language :: Python :: 3.5
Classifier: Programming Language :: Python :: 3.6
Classifier: Programming Language :: Python :: 3.7
